MANIFEST.in
README.rst
requirements.txt
setup.py
version.txt
overwatch/__init__.py
overwatch/errors.py
overwatch/selections.py
overwatch/test.py
overwatch/__pycache__/__init__.cpython-36.pyc
overwatch/__pycache__/errors.cpython-36.pyc
overwatch/__pycache__/selections.cpython-36.pyc
python_overwatch.egg-info/PKG-INFO
python_overwatch.egg-info/SOURCES.txt
python_overwatch.egg-info/dependency_links.txt
python_overwatch.egg-info/requires.txt
python_overwatch.egg-info/top_level.txt