Metadata-Version: 1.0
Name: python-overwatch
Version: 1.0.4
Summary: A Python wrapper for playoverwatch.com
Home-page: https://github.com/alexbotello/python-overwatch
Author: Alexander J. Botello
Author-email: alexander.botello@g.austincc.edu
License: MIT
Platform: UNKNOWN
